s2dl/__init__.py
s2dl/__version__.py
s2dl/s2dl.py
s2dl-0.4.1.dist-info/licenses/LICENSE
s2dl-0.4.1.dist-info/METADATA
s2dl-0.4.1.dist-info/WHEEL
s2dl-0.4.1.dist-info/top_level.txt
s2dl-0.4.1.dist-info/RECORD
