Metadata-Version: 2.4
Name: s2dl
Version: 0.4.1
Summary: S2DL is a Python library for downloading Sentinel-2 L1C and L2A satellite imagery data.
License-Expression: MIT
Project-URL: Homepage, https://github.com/DPIRD-DMA/s2dl
Keywords: sentinel-2,remote-sensing,satellite-imagery,download
Requires-Python: >=3.9
License-File: LICENSE
Requires-Dist: requests>=2.0.0
Requires-Dist: tqdm>=4.0.0
Dynamic: license-file
